yolo_models/bbox_utils.py
yolo_models/image_utils.py
yolo_models/classes.py
yolo_models/__init__.py
yolo_models/torch_transforms.py
yolo_models/log_set/init_log.py
yolo_models/log_set/utc_formatter.py
yolo_models/log_set/__init__.py
yolo_models/nms/nms_native.cpython-39-x86_64-linux-gnu.so
yolo_models/nms/__init__.py
yolo_models/processing/detection_processing.py
yolo_models/processing/base_processing.py
yolo_models/processing/info.py
yolo_models/processing/__init__.py
yolo_models/detection/detector.py
yolo_models/detection/__init__.py
touch_designer_yolo_detection-0.0.2.dist-info/RECORD
touch_designer_yolo_detection-0.0.2.dist-info/top_level.txt
touch_designer_yolo_detection-0.0.2.dist-info/METADATA
touch_designer_yolo_detection-0.0.2.dist-info/WHEEL
