Metadata-Version: 2.1
Name: touch-designer-yolo-detection
Version: 0.0.2
Author: kernelA
Project-URL: Homepage, https://github.com/KernelA/yolo-video-detection-example
Project-URL: Bug Tracker, https://github.com/KernelA/yolo-video-detection-example/issues
Classifier: Intended Audience :: Developers
Classifier: License :: OSI Approved :: MIT License
Classifier: Programming Language :: Python :: 3
Classifier: Environment :: GPU :: NVIDIA CUDA
Classifier: Programming Language :: Cython
Requires-Python: >=3.9
Requires-Dist: opencv-python-headless >=4.7.0.0
Requires-Dist: onnxruntime >=1.11.0
Requires-Dist: matplotlib ~=3.7
Provides-Extra: torch
Requires-Dist: torch ~=2.0.1 ; extra == 'torch'
Requires-Dist: torchvision ~=0.15.2 ; extra == 'torch'
